LICENSE
MANIFEST.in
README.md
setup.py
easydict/__init__.py
easydict/__main__.py
easydict/data/eng-cze.json
easydict/data/help_eng.txt
easydict/data/settings.json
easydict/images/ed_icon.png
easydict/images/ed_pref_icon.png
easydict/images/ed_tray_icon.png
easydict/images/flag_cze.svg
easydict/images/flag_eng.svg
easydict/src/easydict.py
easydict/src/handlers.py
easydict/src/html_generator.py
easydict/src/orjson_storage.py
easydict/src/settings.py
easydict/src/tray_menu.py
easydict/ui/easydict.glade
easydict_gtk.egg-info/PKG-INFO
easydict_gtk.egg-info/SOURCES.txt
easydict_gtk.egg-info/dependency_links.txt
easydict_gtk.egg-info/entry_points.txt
easydict_gtk.egg-info/not-zip-safe
easydict_gtk.egg-info/requires.txt
easydict_gtk.egg-info/top_level.txt