Metadata-Version: 2.1
Name: easydict-gtk
Version: 0.3.6
Summary: The first open source translator which is completely open with dictionary data too.
Home-page: https://github.com/jiri-one/easydict-gtk
Author: Jiří Němec
Author-email: nemec@jiri.one
License: GPL3
Keywords: translator,dict
Platform: UNKNOWN
Classifier: Intended Audience :: End Users/Desktop
Classifier: License :: OSI Approved :: GNU General Public License v3 (GPLv3)
Classifier: Operating System :: POSIX :: Linux
Classifier: Programming Language :: Python
Classifier: Programming Language :: Python :: Implementation :: CPython
Classifier: Programming Language :: Python :: 3
Classifier: Environment :: X11 Applications :: GTK
Requires-Python: >=3.7
License-File: LICENSE
